django_ldaporm-1.3.0.dist-info/licenses/AUTHORS.txt
django_ldaporm-1.3.0.dist-info/licenses/LICENSE.txt
doc/source/conf.py
ldaporm/__init__.py
ldaporm/fields.py
ldaporm/forms.py
ldaporm/ldap.py
ldaporm/managers.py
ldaporm/models.py
ldaporm/options.py
ldaporm/py.typed
ldaporm/restframework.py
ldaporm/server_capabilities.py
ldaporm/typing.py
ldaporm/validators.py
ldaporm/wildewidgets.py
ldaporm/tests/__init__.py
ldaporm/tests/test_f_class.py
ldaporm/tests/test_ldap_manager.py
ldaporm/tests/test_ordering_filter.py
ldaporm/tests/test_restframework.py
ldaporm/tests/test_server_capabilities.py
ldaporm/tests/test_vlv.py
sandbox/manage.py
sandbox/demo/__init__.py
sandbox/demo/gunicorn_config.py
sandbox/demo/logging.py
sandbox/demo/settings.py
sandbox/demo/settings_docker.py
sandbox/demo/settings_test.py
sandbox/demo/urls.py
sandbox/demo/wsgi.py
sandbox/demo/api/__init__.py
sandbox/demo/api/admin.py
sandbox/demo/api/apps.py
sandbox/demo/api/fields.py
sandbox/demo/api/mixins.py
sandbox/demo/api/serializers.py
sandbox/demo/api/urls.py
sandbox/demo/api/migrations/__init__.py
sandbox/demo/api/tests/__init__.py
sandbox/demo/api/tests/test_api_views.py
sandbox/demo/api/views/__init__.py
sandbox/demo/api/views/groups.py
sandbox/demo/api/views/roles.py
sandbox/demo/api/views/users.py
sandbox/demo/core/__init__.py
sandbox/demo/core/apps.py
sandbox/demo/core/forms.py
sandbox/demo/core/models.py
sandbox/demo/core/tests.py
sandbox/demo/core/urls.py
sandbox/demo/core/views.py
sandbox/demo/core/wildewidgets.py
sandbox/demo/core/ldap/__init__.py
sandbox/demo/core/ldap/models.py
sandbox/demo/core/ldap/utils.py
sandbox/demo/core/management/commands/__init__.py
sandbox/demo/core/management/commands/bootstrap.py
sandbox/demo/core/migrations/__init__.py
sandbox/demo/core/password/__init__.py
sandbox/demo/core/password/changer.py
sandbox/demo/core/password/random.py
sandbox/demo/core/password/validator.py
sandbox/demo/core/templatetags/__init__.py
sandbox/demo/core/templatetags/core.py
sandbox/demo/users/__init__.py
sandbox/demo/users/admin.py
sandbox/demo/users/apps.py
django_ldaporm-1.3.0.dist-info/METADATA
django_ldaporm-1.3.0.dist-info/WHEEL
django_ldaporm-1.3.0.dist-info/top_level.txt
django_ldaporm-1.3.0.dist-info/RECORD
